aspis/__init__.py
aspis/common/__init__.py
aspis/common/add.py
aspis/common/add_index.py
aspis/common/add_index_right.py
aspis/common/adjust.py
aspis/common/all.py
aspis/common/all_pass.py
aspis/common/always.py
aspis/common/any.py
aspis/common/any_pass.py
aspis/common/aperture.py
aspis/common/apply.py
aspis/common/apply_spec.py
aspis/common/apply_to.py
aspis/common/assoc.py
aspis/common/compose.py
aspis/common/curry.py
aspis/common/divide.py
aspis/common/equals.py
aspis/common/flip.py
aspis/common/identity.py
aspis/common/multiply.py
aspis/common/pipe.py
aspis/common/prop.py
aspis/common/prop_eq.py
aspis/internal/__init__.py
aspis/internal/eager_partial.py
aspis/internal/utils.py
aspis/internal/errors/__init__.py
aspis/internal/errors/arity_error.py
aspis-0.3.0.dist-info/LICENSE.md
aspis-0.3.0.dist-info/METADATA
aspis-0.3.0.dist-info/WHEEL
aspis-0.3.0.dist-info/top_level.txt
aspis-0.3.0.dist-info/RECORD
